octadist/__init__.py
octadist/__main__.py
octadist/main.py
octadist/octadist_cli.py
octadist/octadist_gui.py
octadist/logo/Icon_Base64.py
octadist/logo/__init__.py
octadist/src/__init__.py
octadist/src/calc.py
octadist/src/draw.py
octadist/src/elements.py
octadist/src/io.py
octadist/src/linear.py
octadist/src/plane.py
octadist/src/plot.py
octadist/src/popup.py
octadist/src/projection.py
octadist/src/scripting.py
octadist/src/structure.py
octadist/src/tools.py
octadist/src/util.py
octadist-3.1.0.dist-info/LICENSE
octadist-3.1.0.dist-info/METADATA
octadist-3.1.0.dist-info/WHEEL
octadist-3.1.0.dist-info/entry_points.txt
octadist-3.1.0.dist-info/top_level.txt
octadist-3.1.0.dist-info/RECORD
