Metadata-Version: 2.1
Name: octadist
Version: 3.1.0
Summary: OctaDist: A tool for calculating distortion parameters in molecule.
Home-page: https://octadist.github.io
Download-URL: https://github.com/OctaDist/OctaDist/releases
Author: Rangsiman Ketkaew et al.
Author-email: rangsiman1993@gmail.com
License: GNU General Public License v3 (GPLv3) on top the license of Python.
Project-URL: Documentation, https://octadist.readthedocs.io/en/latest/
Project-URL: Source, https://github.com/OctaDist/OctaDist
Project-URL: Tracker, https://github.com/OctaDist/OctaDist/issues
Keywords: chemistry,computational chemistry,inorganic chemistry,crystallography,coordination complex,spin-crossover,octahedral distortion parameter,structural analysis,Molecular visualization
Classifier: Environment :: Console
Classifier: Programming Language :: Python
Classifier: Programming Language :: Python :: 3
Classifier: Programming Language :: Python :: 3.7
Classifier: Programming Language :: Python :: 3.8
Classifier: Programming Language :: Python :: 3.9
Classifier: Development Status :: 5 - Production/Stable
Classifier: License :: OSI Approved :: GNU General Public License v3 (GPLv3)
Classifier: Operating System :: OS Independent
Classifier: Operating System :: MacOS :: MacOS X
Classifier: Operating System :: Microsoft :: Windows
Classifier: Operating System :: POSIX
Classifier: Operating System :: POSIX :: AIX
Classifier: Operating System :: POSIX :: BSD
Classifier: Operating System :: POSIX :: Linux
Classifier: Operating System :: POSIX :: SunOS/Solaris
Classifier: Intended Audience :: Science/Research
Classifier: Intended Audience :: Developers
Classifier: Intended Audience :: End Users/Desktop
Classifier: Intended Audience :: Other Audience
Classifier: Natural Language :: English
Classifier: Topic :: Scientific/Engineering :: Chemistry
Classifier: Topic :: Scientific/Engineering :: Mathematics
Classifier: Topic :: Scientific/Engineering :: Visualization
Classifier: Topic :: Software Development :: Libraries :: Python Modules
Classifier: Topic :: Multimedia :: Graphics :: 3D Modeling
Requires-Python: >=3, !=3.0.*, !=3.1.*, !=3.2.*, !=3.3.*, !=3.4.*, !=3.5.*,         !=3.6.*, !=3.10.*, !=3.11.*
License-File: LICENSE
Requires-Dist: numpy
Requires-Dist: scipy
Requires-Dist: matplotlib
Requires-Dist: rmsd
Requires-Dist: pymatgen
Requires-Dist: plotly
